flxtrd/__init__.py
flxtrd/core/__init__.py
flxtrd/core/api_client.py
flxtrd/core/logger.py
flxtrd/core/plugins/__init__.py
flxtrd/core/plugins/auth.py
flxtrd/core/plugins/base.py
flxtrd/core/types.py
flxtrd/core/utils.py
flxtrd/protocols/__init__.py
flxtrd/protocols/ampq.py
flxtrd/protocols/base.py
flxtrd/protocols/rest.py
flxtrd-0.2.9.dist-info/LICENSE
flxtrd-0.2.9.dist-info/METADATA
flxtrd-0.2.9.dist-info/WHEEL
flxtrd-0.2.9.dist-info/RECORD
