Metadata-Version: 2.1
Name: flxtrd
Version: 0.2.9
Summary: Public client API for the flexible energy trading market GLocalFlex.
Home-page: https://github.com/glocalflex/GLocalFlexTrade
Author: glocalflex
Requires-Python: >=3.8,<3.12
Classifier: Programming Language :: Python :: 3
Classifier: Programming Language :: Python :: 3.8
Classifier: Programming Language :: Python :: 3.9
Classifier: Programming Language :: Python :: 3.10
Classifier: Programming Language :: Python :: 3.11
Requires-Dist: pika (>=1.3.1,<2.0.0)
Requires-Dist: requests (>=2.28.0)
Requires-Dist: requests-mock[fixture] (>=1.11.0,<2.0.0)
Project-URL: Documentation, https://glocalflex.github.io/GLocalFlexTrade/
Project-URL: Repository, https://github.com/glocalflex/GLocalFlexTrade
